dynaplex/__init__.py
dynaplex/_core.cp313-win_amd64.pyd
dynaplex/ops.py
dynaplex/utils.py
dynaplex-0.2.0.dist-info/METADATA
dynaplex-0.2.0.dist-info/WHEEL
dynaplex-0.2.0.dist-info/RECORD
