Metadata-Version: 2.2
Name: dynaplex
Version: 0.2.0
Summary: DynaPlex toolbox
Author: Willem van Jaarsveld
Classifier: Programming Language :: Python
Classifier: Programming Language :: Python :: 3
Classifier: Programming Language :: C++
Classifier: Operating System :: OS Independent
Requires-Python: >=3.10
